checkify/__init__.py
checkify/code_checker.py
checkify-0.6.dist-info/LICENSE
checkify-0.6.dist-info/METADATA
checkify-0.6.dist-info/WHEEL
checkify-0.6.dist-info/top_level.txt
checkify-0.6.dist-info/RECORD
