Metadata-Version: 2.1
Name: checkify
Version: 0.6
Summary: Python package that utilizes the power of the GPT API to provide comprehensive code analysis and assistance. It helps you identify errors in code, explains the code logic, and offers valuable suggestions for improvement.
Home-page: https://github.com/aditya0072001/checkify
Author: Tripathi Aditya Prakash
Project-URL: Download Statistics, https://pepy.tech/project/checkify/month
Classifier: Programming Language :: Python :: 3
Classifier: License :: OSI Approved :: MIT License
Classifier: Operating System :: OS Independent
Requires-Python: >=3.6
License-File: LICENSE
Requires-Dist: openai
